templ8/__init__.py
templ8/__main__.py
templ8/core/common/metadata.json
templ8/core/deployments/ansible/metadata.json
templ8/core/deployments/terraform/metadata.json
templ8/core/microservices/angular/metadata.json
templ8/core/microservices/blazor/metadata.json
templ8/core/microservices/django/metadata.json
templ8/core/microservices/express/metadata.json
templ8/core/microservices/flask/metadata.json
templ8/core/microservices/halogen/metadata.json
templ8/core/microservices/react/metadata.json
templ8/core/microservices/spring/metadata.json
templ8/core/microservices/vue/metadata.json
templ8/core/packages/cpp/metadata.json
templ8/core/packages/csharp/metadata.json
templ8/core/packages/java/metadata.json
templ8/core/packages/javascript/metadata.json
templ8/core/packages/purescript/metadata.json
templ8/core/packages/python/metadata.json
templ8/core/packages/typescript/metadata.json
templ8/models/__init__.py
templ8/models/cli.py
templ8/models/collection.py
templ8/models/exceptions.py
templ8/models/flags.py
templ8/models/initialization.py
templ8/models/inputs.py
templ8/models/rename.py
templ8/models/settings.py
templ8/models/timestamps.py
templ8/services/__init__.py
templ8/services/exceptions.py
templ8/services/finders.py
templ8/services/introspection.py
templ8/services/logging.py
templ8/services/mutations.py
templ8/services/renaming.py
templ8/services/runtime.py
templ8/services/schemas.py
templ8/services/templates.py
templ8/utils/__init__.py
templ8/utils/collections/__init__.py
templ8/utils/collections/dicts.py
templ8/utils/collections/lists.py
templ8/utils/extensions/__init__.py
templ8/utils/extensions/format_help.py
templ8/utils/extensions/progress_handler.py
templ8/utils/extensions/store_kv.py
templ8/utils/extensions/switch_formatter.py
templ8/utils/functional/__init__.py
templ8/utils/functional/functions.py
templ8/utils/functional/functors.py
templ8/utils/parsers/__init__.py
templ8/utils/parsers/dataclasses.py
templ8/utils/parsers/exceptions.py
templ8-3.0.0.dist-info/LICENSE.md
templ8-3.0.0.dist-info/METADATA
templ8-3.0.0.dist-info/WHEEL
templ8-3.0.0.dist-info/entry_points.txt
templ8-3.0.0.dist-info/top_level.txt
templ8-3.0.0.dist-info/RECORD
